CHANGELOG.txt
LICENSE.txt
MANIFEST.in
README.txt
setup.py
input_simple/__init__.py
input_simple.egg-info/PKG-INFO
input_simple.egg-info/SOURCES.txt
input_simple.egg-info/dependency_links.txt
input_simple.egg-info/requires.txt
input_simple.egg-info/top_level.txt