Metadata-Version: 1.1
Name: input-simple
Version: 1.0.1
Summary: A Library for facilitating input operations
Home-page: https://github.com/saikatsahana77/input_simple
Author: Saikat Sahana
Author-email: saikatsahana91@gmail.com
License: MIT
Keywords: inputmodule input inputsimple
Platform: UNKNOWN
Classifier: Development Status :: 5 - Production/Stable
Classifier: Intended Audience :: Education
Classifier: Operating System :: Microsoft :: Windows :: Windows 10
Classifier: Operating System :: POSIX :: Linux
Classifier: License :: OSI Approved :: MIT License
Classifier: Programming Language :: Python :: 3
